fabric_python_helper/__init__.py
fabric_python_helper/graph_api.py
fabric_python_helper/pbi_admin.py
fabric_python_helper-0.3.0.dist-info/licenses/LICENSE
fabric_python_helper-0.3.0.dist-info/licenses/NOTICE
fabric_python_helper-0.3.0.dist-info/METADATA
fabric_python_helper-0.3.0.dist-info/WHEEL
fabric_python_helper-0.3.0.dist-info/top_level.txt
fabric_python_helper-0.3.0.dist-info/RECORD
