Metadata-Version: 2.4
Name: fabric_python_helper
Version: 0.3.0
Summary: Collection of useful python code for automation in Microsoft Fabric.
Home-page: https://github.com/ArchwayTrust/Fabric-PythonHelper
Author: Ben Dobbs
Author-email: bdobbs@archwaytrust.co.uk
License-File: LICENSE
License-File: NOTICE
Requires-Dist: msal
Requires-Dist: requests
Dynamic: author
Dynamic: author-email
Dynamic: description
Dynamic: description-content-type
Dynamic: home-page
Dynamic: license-file
Dynamic: requires-dist
Dynamic: summary
